package_wish/Preprocess.py
package_wish/__init__.py
package_wish-1.0.0.dist-info/LICENSE
package_wish-1.0.0.dist-info/METADATA
package_wish-1.0.0.dist-info/WHEEL
package_wish-1.0.0.dist-info/top_level.txt
package_wish-1.0.0.dist-info/RECORD
